py_p_audio_core.cp311-win_amd64.pyd
py_p_audio_native/__init__.py
py_p_audio_native/api.py
py_p_audio_native/exceptions.py
py_p_audio_native/py_p_audio_core.cp311-win_amd64.pyd
py_p_audio_native/py_p_audio_core.pyd
py_p_audio_native-2.0.4.dist-info/METADATA
py_p_audio_native-2.0.4.dist-info/WHEEL
py_p_audio_native-2.0.4.dist-info/entry_points.txt
py_p_audio_native-2.0.4.dist-info/top_level.txt
py_p_audio_native-2.0.4.dist-info/RECORD
