Metadata-Version: 2.4
Name: py-p-audio-native
Version: 2.0.4
Summary: 高性能な Python オーディオライブラリ - ネイティブ C++ コア搭載
Home-page: https://github.com/hiroshi-tamura/py-p-audio-native
Author: hiroshi-tamura
Author-email: 
License: MIT
Project-URL: Homepage, https://github.com/hiroshi-tamura/py-p-audio-native
Project-URL: Repository, https://github.com/hiroshi-tamura/py-p-audio-native.git
Project-URL: Issues, https://github.com/hiroshi-tamura/py-p-audio-native/issues
Keywords: audio,recording,playback,WASAPI,ASIO,native,pybind11
Classifier: Development Status :: 5 - Production/Stable
Classifier: Intended Audience :: Developers
Classifier: License :: OSI Approved :: MIT License
Classifier: Operating System :: Microsoft :: Windows
Classifier: Programming Language :: C++
Classifier: Programming Language :: Python :: 3.8
Classifier: Programming Language :: Python :: 3.9
Classifier: Programming Language :: Python :: 3.10
Classifier: Programming Language :: Python :: 3.11
Classifier: Programming Language :: Python :: 3.12
Classifier: Topic :: Multimedia :: Sound/Audio :: Capture/Recording
Classifier: Topic :: Multimedia :: Sound/Audio :: Players
Classifier: Topic :: Software Development :: Libraries :: Python Modules
Requires-Python: >=3.8
Dynamic: home-page
Dynamic: requires-python
